mob_tfm/__init__.py
mob_tfm/commands/__init__.py
mob_tfm/commands/config.py
mob_tfm/commands/doctor.py
mob_tfm/commands/explain.py
mob_tfm/commands/generate.py
mob_tfm/commands/parse.py
mob_tfm/commands/unspine.py
mob_tfm/commands/version.py
mob_tfm/exceptions.py
mob_tfm/main.py
mob_tfm/utils/__init__.py
mob_tfm/utils/db_utils.py
mob_tfm/utils/generate_utils.py
mob_tfm/utils/parse_utils.py
mob_tfm/utils/tfm_generators.py
mob_tfm/utils/utils.py
mob_tfm-0.2.0.dist-info/METADATA
mob_tfm-0.2.0.dist-info/WHEEL
mob_tfm-0.2.0.dist-info/entry_points.txt
mob_tfm-0.2.0.dist-info/licenses/LICENSE
mob_tfm-0.2.0.dist-info/RECORD
