Metadata-Version: 2.4
Name: mob-tfm
Version: 0.2.0
Summary: A streaming CLI tool to *mob*(fills) SQL/MariaDB databases with mock data, built on Faker and designed for both flexibility and scale.
License-Expression: MIT
License-File: LICENSE
Keywords: SQL,MariaDB,python3,cli,terminal,database seeding,mock data
Author: gitmobkab
Author-email: richmondaurel77@gmail.com
Requires-Python: >=3.13
Classifier: Development Status :: 3 - Alpha
Classifier: Environment :: Console
Classifier: Framework :: IPython
Classifier: Intended Audience :: Developers
Classifier: Intended Audience :: Education
Classifier: Operating System :: MacOS
Classifier: Operating System :: Microsoft :: Windows
Classifier: Operating System :: POSIX :: Linux
Classifier: Programming Language :: Python :: 3
Classifier: Programming Language :: Python :: 3.13
Classifier: Programming Language :: Python :: 3.14
Classifier: Topic :: Terminals
Classifier: Topic :: Terminals :: Terminal Emulators/X Terminals
Requires-Dist: faker (>=38.2.0,<39.0.0)
Requires-Dist: mariadb (>=1.1.14,<2.0.0)
Requires-Dist: typer (>=0.20.0,<0.21.0)
Project-URL: Repository, https://github.com/gitmobkab/mob-tfm/
